{
  "slug": "leather-hide-yield-calculator",
  "toolName": "Leather Hide Coverage Calculator",
  "tagline": "Estimate usable leather from a hide",
  "title": "Leather Hide Coverage Calculator — Free Online Calculator",
  "metaDescription": "Estimate usable leather from a hide. Free, instant, no signup required.",
  "keywords": "leather, hide, leather craft, square feet, leather yield",
  "domain": "crunchmilk.com",
  "primaryColor": "#ec4899",
  "primaryDarkColor": "#db2777",
  "ogTitle": "Leather Hide Coverage Calculator — Free Online Calculator",
  "ogDescription": "Free leather hide coverage calculator. Estimate usable leather from a hide. No signup required.",
  "twitterDescription": "Free leather hide coverage calculator. Estimate usable leather from a hide.",
  "jsonLdDescription": "Leather Hide Coverage Calculator: Estimate usable leather from a hide. Enter your values for instant results.",
  "calculatorHTML": "<div class=\"calc-card\">\n  <h2>Leather Hide Coverage Calculator</h2>\n  <div style=\"display:grid;grid-template-columns:1fr 1fr 1fr;gap:12px\">\n    <div class=\"input-group\" style=\"margin-bottom:0\">\n      <label for=\"hideSize\">Hide Size (sq ft)</label>\n      <input type=\"number\" id=\"hideSize\" value=\"undefined\" min=\"1\" max=\"60\" step=\"1\" inputmode=\"decimal\">\n    </div>\n    <div class=\"input-group\" style=\"margin-bottom:0\">\n      <label for=\"waste\">Waste/Defect (%)</label>\n      <input type=\"number\" id=\"waste\" value=\"undefined\" min=\"5\" max=\"50\" step=\"5\" inputmode=\"decimal\">\n    </div>\n    <div class=\"input-group\" style=\"margin-bottom:0\">\n      <label for=\"pieceArea\">Piece Size (sq inches)</label>\n      <input type=\"number\" id=\"pieceArea\" value=\"undefined\" min=\"1\" max=\"500\" step=\"1\" inputmode=\"decimal\">\n    </div>\n  </div>\n\n  <button type=\"button\" class=\"convert-btn\" id=\"calcBtn\">Calculate</button>\n\n  <div class=\"result\" id=\"result\" role=\"status\" aria-live=\"polite\">\n    <div class=\"result-row\">\n      <div class=\"result-item\">\n        <div class=\"result-label\">Usable Area</div>\n        <div class=\"result-value\" id=\"usable\">—</div>\n      </div>\n      <div class=\"result-item\">\n        <div class=\"result-label\">Pieces You Can Cut</div>\n        <div class=\"result-value\" id=\"pieces\">—</div>\n      </div>\n    </div>\n    <div class=\"result-tip\" id=\"resultTip\"></div>\n  </div>\n</div>",
  "howItWorks": {
    "intro": "This leather hide coverage calculator uses established formulas to provide accurate results.",
    "rules": [
      {
        "name": "Usable Area",
        "formula": "Usable = Hide Size × (1 - Waste%)",
        "explanation": "Total hide minus defects and unusable edges."
      }
    ],
    "outro": "Results are estimates. Consult a professional for critical decisions."
  },
  "faq": [
    {
      "q": "How much waste from a leather hide?",
      "a": "Typically 20-30% waste from edges, belly, and defects."
    },
    {
      "q": "What size hide do I need?",
      "a": "A full cowhide is 40-55 sq ft, a half hide is 20-25 sq ft."
    }
  ],
  "relatedTools": [],
  "howWeCalculate": {
    "intro": "This leather hide coverage calculator uses established formulas and current data to provide accurate estimates.",
    "steps": [
      "Enter your specific values into the calculator fields above",
      "Our algorithm applies the relevant formulas using your inputs",
      "Results are calculated instantly in your browser — nothing is sent to a server",
      "Review the detailed breakdown to understand how each factor affects your result"
    ],
    "disclaimer": "These calculations are estimates based on standard formulas. For critical decisions, always consult a qualified professional."
  },
  "whenToUse": {
    "intro": "This leather hide coverage calculator is designed for anyone who needs quick, reliable estimates.",
    "scenarios": [
      "When you need a quick estimate before committing to a purchase or project",
      "When comparing different options or scenarios side by side",
      "When planning a budget and need to understand potential costs",
      "When you want to verify a quote or estimate you've received",
      "When teaching or learning about the concepts behind these calculations"
    ]
  },
  "category": "crafts",
  "lastUpdated": "2026-03-11"
}